fds/__init__.py
fds/sdk/__init__.py
fds/sdk/PAEngine/__init__.py
fds/sdk/PAEngine/api_client.py
fds/sdk/PAEngine/configuration.py
fds/sdk/PAEngine/exceptions.py
fds/sdk/PAEngine/model_utils.py
fds/sdk/PAEngine/rest.py
fds/sdk/PAEngine/api/__init__.py
fds/sdk/PAEngine/api/accounts_api.py
fds/sdk/PAEngine/api/column_statistics_api.py
fds/sdk/PAEngine/api/columns_api.py
fds/sdk/PAEngine/api/components_api.py
fds/sdk/PAEngine/api/configurations_api.py
fds/sdk/PAEngine/api/currencies_api.py
fds/sdk/PAEngine/api/dates_api.py
fds/sdk/PAEngine/api/documents_api.py
fds/sdk/PAEngine/api/frequencies_api.py
fds/sdk/PAEngine/api/groups_api.py
fds/sdk/PAEngine/api/linked_pa_templates_api.py
fds/sdk/PAEngine/api/pa_calculations_api.py
fds/sdk/PAEngine/api/pricing_sources_api.py
fds/sdk/PAEngine/api/templated_pa_components_api.py
fds/sdk/PAEngine/api/unlinked_pa_templates_api.py
fds/sdk/PAEngine/apis/__init__.py
fds/sdk/PAEngine/model/__init__.py
fds/sdk/PAEngine/model/account_directories.py
fds/sdk/PAEngine/model/account_directories_root.py
fds/sdk/PAEngine/model/calculation_meta.py
fds/sdk/PAEngine/model/calculation_status.py
fds/sdk/PAEngine/model/calculation_status_meta.py
fds/sdk/PAEngine/model/calculation_status_root.py
fds/sdk/PAEngine/model/calculation_unit_status.py
fds/sdk/PAEngine/model/calculation_unit_status_meta.py
fds/sdk/PAEngine/model/calculations_summary.py
fds/sdk/PAEngine/model/calculations_summary_root.py
fds/sdk/PAEngine/model/client_error_response.py
fds/sdk/PAEngine/model/column.py
fds/sdk/PAEngine/model/column_root.py
fds/sdk/PAEngine/model/column_statistic.py
fds/sdk/PAEngine/model/column_statistic_root.py
fds/sdk/PAEngine/model/column_summary.py
fds/sdk/PAEngine/model/column_summary_root.py
fds/sdk/PAEngine/model/component_summary.py
fds/sdk/PAEngine/model/component_summary_root.py
fds/sdk/PAEngine/model/currency.py
fds/sdk/PAEngine/model/currency_root.py
fds/sdk/PAEngine/model/date_parameters_summary.py
fds_sdk_paengine-2.2.2.dist-info/licenses/LICENSE
fds_sdk_paengine-2.2.2.dist-info/METADATA
fds_sdk_paengine-2.2.2.dist-info/WHEEL
fds_sdk_paengine-2.2.2.dist-info/top_level.txt
fds_sdk_paengine-2.2.2.dist-info/RECORD
